fondsweb/__init__.py
fondsweb/fondsweb.py
fondsweb/fondsweb_config.py
fondsweb/resources/.gitkeep
fondsweb_scraper-0.1.4.dist-info/METADATA
fondsweb_scraper-0.1.4.dist-info/WHEEL
fondsweb_scraper-0.1.4.dist-info/licenses/LICENSE
fondsweb_scraper-0.1.4.dist-info/RECORD
