Metadata-Version: 2.4
Name: fondsweb-scraper
Version: 0.1.4
Summary: Web scraper for ETF data from fondsweb website.
Project-URL: Homepage, https://github.com/asmaier/fondsweb
Author-email: asmaier <asmaier@web.de>
License-Expression: MIT
License-File: LICENSE
Classifier: Development Status :: 4 - Beta
Classifier: License :: OSI Approved :: MIT License
Classifier: Natural Language :: English
Classifier: Natural Language :: German
Classifier: Programming Language :: Python :: 3.12
Classifier: Topic :: Office/Business :: Financial :: Investment
Requires-Python: >=3.12
Requires-Dist: cloudscraper>=1.2.71
Requires-Dist: lxml>=5.4.0
Requires-Dist: pandas>=2.2.3
